MANIFEST.in
README.md
README.rst
setup.py
bsw/__init__.py
bsw/__main__.py
bsw/bsw.py
bsw/files.py
bsw/includes.py
bsw/pages.py
bsw/templates.py
bsw.egg-info/PKG-INFO
bsw.egg-info/SOURCES.txt
bsw.egg-info/dependency_links.txt
bsw.egg-info/entry_points.txt
bsw.egg-info/top_level.txt
bsw/templates/default/pages/index.html
bsw/templates/default/pages/about/index.html
bsw/templates/default/pages/blog/index.html
bsw/templates/default/pages/blog/2016/05/10/my_first_blog_post/index.html
bsw/templates/default/static/.empty
bsw/templates/default/templates/base.html
bsw/templates/default/templates/blog.html
bsw/templates/default/templates/static/main.css