Metadata-Version: 1.0
Name: bsw
Version: 1.0.7
Summary: bsw - Build Static Web, a simple static website builder.
Home-page: https://github.com/davb5/bsw
Author: Dave Barker
Author-email: david@dbark.co.uk
License: UNKNOWN
Platform: UNKNOWN
